full_adder.v
module full_adder(s, cout, a, b, cin);

input a,b,cin;
output s,cout;
wire w1, w2, w3;

//Both Circuits
xor(w1, a, b);

// Summation circuit
xor(s, w1, cin);

// carry-out circuit
or(cout, w2, w3);
and(w2, w1, cin);
and(w3, a, b);

endmodule

adder_subtractor.v
//https://tinyurl.com/y435nrgr
module adder_subtractor( s, overflow, enable, a, b, op);
input enable;  //enable module
input [7:0] a; //var1
input [7:0] b; //var2
output[7:0] s; //output
output overflow; //indicates if there was an over flow
input op;      // 0 = add, 1 = subtract

//Carry and xor wires
wire [6:0] carry;
wire [7:0]  bxor;
wire last_cout;

//xor chain for subtraction (take a look at the diagram)
xor(bxor[0], b[0], op);
xor(bxor[1], b[1], op);
xor(bxor[2], b[2], op);
xor(bxor[3], b[3], op);
xor(bxor[4], b[4], op);
xor(bxor[5], b[5], op);
xor(bxor[6], b[6], op);
xor(bxor[7], b[7], op);

//The cascaded full adders
full_adder a0(s[0], carry[0], a[0], bxor[0], op);
full_adder a1(s[1], carry[1], a[1], bxor[1], carry[0]);
full_adder a2(s[2], carry[2], a[2], bxor[2], carry[1]);
full_adder a3(s[3], carry[3], a[3], bxor[3], carry[2]);
full_adder a4(s[4], carry[4], a[4], bxor[4], carry[3]);
full_adder a5(s[5], carry[5], a[5], bxor[5], carry[4]);
full_adder a6(s[6], carry[6], a[6], bxor[6], carry[5]);
full_adder a7(s[7], last_cout,a[7], bxor[7], carry[6]);

//xor that manages overflow
xor(overflow, carry[6], last_cout);

endmodule

adder_subtractor_tb.v
`timescale 1ps/1ps

module adder_subtractor_tb;
reg signed [7:0] a;
reg signed [7:0] b;
reg op;
reg enable;
wire signed [7:0] s;
wire overflow;

initial
	begin
		$dumpfile("adder_subtractor.vcd");
		$dumpvars(0,Johnson);
		$display("  a   b op     s overflow");
		$monitor("%d %d  %d  | %d  %d", a, b, op, s, overflow);
		#0  enable = 1'b1;
		//edge cases around 0
		#0  a = 8'b1; 	b =  8'd1; 	op = 1'b0;
		#50 a = 8'd1;  	b =  8'd1; 	op = 1'b1;
		#50 a = 8'd1;  	b = -8'd1; 	op = 1'b0;
		#50 a = 8'd1;  	b = -8'd1; 	op = 1'b1;
		#50 a = -8'd1; 	b =  8'd1; 	op = 1'b0;
		#50 a = -8'd1; 	b =  8'd1; 	op = 1'b1;
		#50 a = -8'd1; 	b = -8'd1; 	op = 1'b0;
		#50 a = -8'd1; 	b = -8'd1; 	op = 1'b1;
		
		//edge cases around 128
		#50 a =  8'd127;	b =  8'd1; 	op = 1'b0;
		#50 a =  8'd127;	b =  8'd1; 	op = 1'b1;
		#50 a =  8'd127;	b = -8'd1; 	op = 1'b0;
		#50 a =  8'd127;	b = -8'd1;  op = 1'b1;
		#50 a = -8'd127;	b =  8'd1; 	op = 1'b0;
		#50 a = -8'd127;	b =  8'd1; 	op = 1'b1;
		#50 a = -8'd127;	b = -8'd1; 	op = 1'b0;
		#50 a = -8'd127;	b = -8'd1; 	op = 1'b1;
		#50 $finish;
	end

adder_subtractor Johnson(s,overflow,enable,a,b,op);

endmodule

adder_subtractor.vcd
$date
	Tue May 14 12:11:35 2019
$end
$version
	Icarus Verilog
$end
$timescale
	1ps
$end
$scope module adder_subtractor_tb $end
$scope module Johnson $end
$var wire 8 ! a [7:0] $end
$var wire 8 " b [7:0] $end
$var wire 1 # enable $end
$var wire 1 $ op $end
$var wire 1 % overflow $end
$var wire 8 & s [7:0] $end
$var wire 1 ' last_cout $end
$var wire 7 ( carry [6:0] $end
$var wire 8 ) bxor [7:0] $end
$scope module a0 $end
$var wire 1 * a $end
$var wire 1 + b $end
$var wire 1 $ cin $end
$var wire 1 , cout $end
$var wire 1 - s $end
$var wire 1 . w1 $end
$var wire 1 / w2 $end
$var wire 1 0 w3 $end
$upscope $end
$scope module a1 $end
$var wire 1 1 a $end
$var wire 1 2 b $end
$var wire 1 3 cin $end
$var wire 1 4 cout $end
$var wire 1 5 s $end
$var wire 1 6 w1 $end
$var wire 1 7 w2 $end
$var wire 1 8 w3 $end
$upscope $end
$scope module a2 $end
$var wire 1 9 a $end
$var wire 1 : b $end
$var wire 1 ; cin $end
$var wire 1 < cout $end
$var wire 1 = s $end
$var wire 1 > w1 $end
$var wire 1 ? w2 $end
$var wire 1 @ w3 $end
$upscope $end
$scope module a3 $end
$var wire 1 A a $end
$var wire 1 B b $end
$var wire 1 C cin $end
$var wire 1 D cout $end
$var wire 1 E s $end
$var wire 1 F w1 $end
$var wire 1 G w2 $end
$var wire 1 H w3 $end
$upscope $end
$scope module a4 $end
$var wire 1 I a $end
$var wire 1 J b $end
$var wire 1 K cin $end
$var wire 1 L cout $end
$var wire 1 M s $end
$var wire 1 N w1 $end
$var wire 1 O w2 $end
$var wire 1 P w3 $end
$upscope $end
$scope module a5 $end
$var wire 1 Q a $end
$var wire 1 R b $end
$var wire 1 S cin $end
$var wire 1 T cout $end
$var wire 1 U s $end
$var wire 1 V w1 $end
$var wire 1 W w2 $end
$var wire 1 X w3 $end
$upscope $end
$scope module a6 $end
$var wire 1 Y a $end
$var wire 1 Z b $end
$var wire 1 [ cin $end
$var wire 1 \ cout $end
$var wire 1 ] s $end
$var wire 1 ^ w1 $end
$var wire 1 _ w2 $end
$var wire 1 ` w3 $end
$upscope $end
$scope module a7 $end
$var wire 1 a a $end
$var wire 1 b b $end
$var wire 1 c cin $end
$var wire 1 ' cout $end
$var wire 1 d s $end
$var wire 1 e w1 $end
$var wire 1 f w2 $end
$var wire 1 g w3 $end
$upscope $end
$upscope $end
$upscope $end
$enddefinitions $end
#0
$dumpvars
0g
0f
0e
0d
0c
0b
0a
0`
0_
0^
0]
0\
0[
0Z
0Y
0X
0W
0V
0U
0T
0S
0R
0Q
0P
0O
0N
0M
0L
0K
0J
0I
0H
0G
0F
0E
0D
0C
0B
0A
0@
0?
0>
0=
0<
0;
0:
09
08
07
06
15
04
13
02
01
10
0/
0.
0-
1,
1+
1*
b1 )
b1 (
0'
b10 &
0%
0$
1#
b1 "
b1 !
$end
#50
1'
1f
0%
1c
1\
1_
1[
1T
1W
1S
1L
1O
1K
1D
1G
1C
1<
1?
1;
13
14
1/
b1111111 (
1,
05
17
0=
0E
0M
0U
0]
0d
1.
00
16
1>
1F
1N
1V
1^
1e
0+
12
1:
1B
1J
1R
1Z
1b
b11111110 )
b0 &
0-
1$
#100
1'
0d
1f
0%
1c
1\
0]
1_
1[
1T
0U
1W
1S
1L
0M
1O
1K
1D
0E
1G
1C
1<
0=
1?
1;
14
05
17
0.
10
13
1+
b1111111 (
1,
b11111111 )
b0 &
0-
0/
0$
b11111111 "
#150
0;
0C
0K
0S
0[
0c
0%
13
04
0<
0D
0L
0T
0\
0'
1/
b1 (
1,
15
07
0=
0?
0E
0G
0M
0O
0U
0W
0]
0_
0d
0f
1.
00
06
0>
0F
0N
0V
0^
0e
0+
02
0:
0B
0J
0R
0Z
0b
b0 )
b10 &
0-
1$
#200
1'
1f
0%
1c
1\
1_
1[
1T
1W
1S
1L
1O
1K
1D
1G
1C
1<
1?
1;
14
0.
10
13
05
17
0=
0E
0M
0U
0]
0d
1+
b1111111 (
1,
16
1>
1F
1N
1V
1^
1e
b1 )
b0 &
0-
0/
11
19
1A
1I
1Q
1Y
1a
0$
b1 "
b11111111 !
#250
13
1/
b1111111 (
1,
15
07
1=
0?
1E
0G
1M
0O
1U
0W
1]
0_
1d
0f
1.
00
06
18
0>
1@
0F
1H
0N
1P
0V
1X
0^
1`
0e
1g
0+
12
1:
1B
1J
1R
1Z
1b
b11111110 )
b11111110 &
0-
1$
#300
15
0.
10
13
1+
b1111111 (
1,
b11111111 )
b11111110 &
0-
0/
0$
b11111111 "
#350
13
1;
1C
1K
1S
1[
1c
0%
1/
1,
05
17
14
0=
1?
1<
0E
1G
1D
0M
1O
1L
0U
1W
1T
0]
1_
b1111111 (
1\
0d
1f
1'
1.
00
16
08
1>
0@
1F
0H
1N
0P
1V
0X
1^
0`
1e
0g
0+
02
0:
0B
0J
0R
0Z
0b
b0 )
b0 &
0-
1$
#400
1c
1\
0]
1_
1[
1T
0U
1W
1S
1L
0M
1O
1K
1D
0E
1G
1C
1<
0=
1?
1;
14
1%
05
17
0'
0.
10
13
1d
0f
1+
b1111111 (
1,
0e
b1 )
b10000000 &
0-
0/
0a
0$
b1 "
b1111111 !
#450
0%
13
1'
1/
b1111111 (
1,
15
07
1=
0?
1E
0G
1M
0O
1U
0W
1]
0_
0d
1f
1.
00
06
18
0>
1@
0F
1H
0N
1P
0V
1X
0^
1`
1e
0+
12
1:
1B
1J
1R
1Z
1b
b11111110 )
b1111110 &
0-
1$
#500
15
0.
10
13
1+
b1111111 (
1,
b11111111 )
b1111110 &
0-
0/
0$
b11111111 "
#550
1%
13
1;
1C
1K
1S
1[
1c
0'
1/
1,
05
17
14
0=
1?
1<
0E
1G
1D
0M
1O
1L
0U
1W
1T
0]
1_
b1111111 (
1\
1d
0f
1.
00
16
08
1>
0@
1F
0H
1N
0P
1V
0X
1^
0`
0e
0+
02
0:
0B
0J
0R
0Z
0b
b0 )
b10000000 &
0-
1$
#600
0;
0C
0K
0S
0[
0c
0%
04
0<
0D
0L
0T
0\
0'
0.
10
13
15
07
0=
0?
0E
0G
0M
0O
0U
0W
0]
0_
1d
0f
1+
b1 (
1,
06
0>
0F
0N
0V
0^
1e
b1 )
b10000010 &
0-
0/
01
09
0A
0I
0Q
0Y
1a
0$
b1 "
b10000001 !
#650
1c
1\
1_
1[
1T
1W
1S
1L
1O
1K
1D
1G
1C
1<
1?
1;
13
14
0%
1/
b1111111 (
1,
05
17
0=
0E
0M
0U
0]
1d
1'
1.
00
16
1>
1F
1N
1V
1^
0e
1g
0+
12
1:
1B
1J
1R
1Z
1b
b11111110 )
b10000000 &
0-
1$
#700
1d
0%
1c
1\
0]
1_
1[
1T
0U
1W
1S
1L
0M
1O
1K
1D
0E
1G
1C
1<
0=
1?
1;
14
05
17
0.
10
13
1+
b1111111 (
1,
b11111111 )
b10000000 &
0-
0/
0$
b11111111 "
#750
0;
0C
0K
0S
0[
0c
13
04
0<
0D
0L
0T
0\
0%
1/
b1 (
1,
15
07
0=
0?
0E
0G
0M
0O
0U
0W
0]
0_
1d
0f
0'
1.
00
06
0>
0F
0N
0V
0^
1e
0g
0+
02
0:
0B
0J
0R
0Z
0b
b0 )
b10000010 &
0-
1$
