full_adder.v
module full_adder(s, cout, a, b, cin);

input a,b,cin;
output s,cout;
wire w1, w2, w3;

//Both Circuits
xor(w1, a, b);

// Summation circuit
xor(s, w1, cin);

// carry-out circuit
or(cout, w2, w3);
and(w2, w1, cin);
and(w3, a, b);

endmodule

adder_subtractor.v
//Module by Ryan Thompson
//https://tinyurl.com/y435nrgr
module adder_subtractor( s, overflow, a, b, op);
input  signed [7:0] a; //var1
input  signed [7:0] b; //var2
output signed [7:0] s; //output
output overflow; //indicates if there was an over flow
input  op;      // 0 -> a+b, 1 -> a-b

//Carry and xor wires
wire [6:0] carry;
wire [7:0] bxor; //wires connecting to the FAs
wire last_cout;

//xor chain for subtraction (take a look at the diagram)
xor(bxor[0], b[0], op);
xor(bxor[1], b[1], op);
xor(bxor[2], b[2], op);
xor(bxor[3], b[3], op);
xor(bxor[4], b[4], op);
xor(bxor[5], b[5], op);
xor(bxor[6], b[6], op);
xor(bxor[7], b[7], op);

//The cascaded full adders
full_adder a0(s[0], carry[0], a[0], bxor[0], op);
full_adder a1(s[1], carry[1], a[1], bxor[1], carry[0]);
full_adder a2(s[2], carry[2], a[2], bxor[2], carry[1]);
full_adder a3(s[3], carry[3], a[3], bxor[3], carry[2]);
full_adder a4(s[4], carry[4], a[4], bxor[4], carry[3]);
full_adder a5(s[5], carry[5], a[5], bxor[5], carry[4]);
full_adder a6(s[6], carry[6], a[6], bxor[6], carry[5]);
full_adder a7(s[7], last_cout,a[7], bxor[7], carry[6]);

//xor that manages overflow
xor(overflow, carry[6], last_cout);

endmodule

adder_subtractor_tb.v
`timescale 1ps/1ps

module adder_subtractor_tb;
reg signed [7:0] a;
reg signed [7:0] b;
reg op;
wire signed [7:0] s;
wire overflow;

initial
	begin
		$dumpfile("adder_subtractor.vcd");
		$dumpvars(0,Johnson);
		$display("  a   b op     s overflow");
		$monitor("%d %d  %d  | %d  %d", a, b, op, s, overflow);
		
		//edge cases around 0
		#0  a = 8'b1; 	b =  8'd1; 	op = 1'b0;
		#50 a = 8'd1;  	b =  8'd1; 	op = 1'b1;
		#50 a = 8'd1;  	b = -8'd1; 	op = 1'b0;
		#50 a = 8'd1;  	b = -8'd1; 	op = 1'b1;
		#50 a = -8'd1; 	b =  8'd1; 	op = 1'b0;
		#50 a = -8'd1; 	b =  8'd1; 	op = 1'b1;
		#50 a = -8'd1; 	b = -8'd1; 	op = 1'b0;
		#50 a = -8'd1; 	b = -8'd1; 	op = 1'b1;
		
		//edge cases around 128
		#50 a =  8'd127;	b =  8'd1; 	op = 1'b0;
		#50 a =  8'd127;	b =  8'd1; 	op = 1'b1;
		#50 a =  8'd127;	b = -8'd1; 	op = 1'b0;
		#50 a =  8'd127;	b = -8'd1;  op = 1'b1;
		#50 a = -8'd127;	b =  8'd1; 	op = 1'b0;
		#50 a = -8'd127;	b =  8'd1; 	op = 1'b1;
		#50 a = -8'd127;	b = -8'd1; 	op = 1'b0;
		#50 a = -8'd127;	b = -8'd1; 	op = 1'b1;
		
		//Cases previously found having and error
		#50 a = -8'd127;	b = -8'd15; op = 1'b0;
		#50 $finish;
	end

adder_subtractor Johnson(s,overflow,a,b,op);

endmodule

adder_subtractor.vcd
$date
	Sat May 18 03:26:02 2019
$end
$version
	Icarus Verilog
$end
$timescale
	1ps
$end
$scope module adder_subtractor_tb $end
$scope module Johnson $end
$var wire 8 ! a [7:0] $end
$var wire 8 " b [7:0] $end
$var wire 1 # op $end
$var wire 1 $ overflow $end
$var wire 8 % s [7:0] $end
$var wire 1 & last_cout $end
$var wire 7 ' carry [6:0] $end
$var wire 8 ( bxor [7:0] $end
$scope module a0 $end
$var wire 1 ) a $end
$var wire 1 * b $end
$var wire 1 # cin $end
$var wire 1 + cout $end
$var wire 1 , s $end
$var wire 1 - w1 $end
$var wire 1 . w2 $end
$var wire 1 / w3 $end
$upscope $end
$scope module a1 $end
$var wire 1 0 a $end
$var wire 1 1 b $end
$var wire 1 2 cin $end
$var wire 1 3 cout $end
$var wire 1 4 s $end
$var wire 1 5 w1 $end
$var wire 1 6 w2 $end
$var wire 1 7 w3 $end
$upscope $end
$scope module a2 $end
$var wire 1 8 a $end
$var wire 1 9 b $end
$var wire 1 : cin $end
$var wire 1 ; cout $end
$var wire 1 < s $end
$var wire 1 = w1 $end
$var wire 1 > w2 $end
$var wire 1 ? w3 $end
$upscope $end
$scope module a3 $end
$var wire 1 @ a $end
$var wire 1 A b $end
$var wire 1 B cin $end
$var wire 1 C cout $end
$var wire 1 D s $end
$var wire 1 E w1 $end
$var wire 1 F w2 $end
$var wire 1 G w3 $end
$upscope $end
$scope module a4 $end
$var wire 1 H a $end
$var wire 1 I b $end
$var wire 1 J cin $end
$var wire 1 K cout $end
$var wire 1 L s $end
$var wire 1 M w1 $end
$var wire 1 N w2 $end
$var wire 1 O w3 $end
$upscope $end
$scope module a5 $end
$var wire 1 P a $end
$var wire 1 Q b $end
$var wire 1 R cin $end
$var wire 1 S cout $end
$var wire 1 T s $end
$var wire 1 U w1 $end
$var wire 1 V w2 $end
$var wire 1 W w3 $end
$upscope $end
$scope module a6 $end
$var wire 1 X a $end
$var wire 1 Y b $end
$var wire 1 Z cin $end
$var wire 1 [ cout $end
$var wire 1 \ s $end
$var wire 1 ] w1 $end
$var wire 1 ^ w2 $end
$var wire 1 _ w3 $end
$upscope $end
$scope module a7 $end
$var wire 1 ` a $end
$var wire 1 a b $end
$var wire 1 b cin $end
$var wire 1 & cout $end
$var wire 1 c s $end
$var wire 1 d w1 $end
$var wire 1 e w2 $end
$var wire 1 f w3 $end
$upscope $end
$upscope $end
$upscope $end
$enddefinitions $end
#0
$dumpvars
0f
0e
0d
0c
0b
0a
0`
0_
0^
0]
0\
0[
0Z
0Y
0X
0W
0V
0U
0T
0S
0R
0Q
0P
0O
0N
0M
0L
0K
0J
0I
0H
0G
0F
0E
0D
0C
0B
0A
0@
0?
0>
0=
0<
0;
0:
09
08
07
06
05
14
03
12
01
00
1/
0.
0-
0,
1+
1*
1)
b1 (
b1 '
0&
b10 %
0$
0#
b1 "
b1 !
$end
#50
1&
1e
0$
1b
1[
1^
1Z
1S
1V
1R
1K
1N
1J
1C
1F
1B
1;
1>
1:
12
13
1.
b1111111 '
1+
04
16
0<
0D
0L
0T
0\
0c
1-
0/
15
1=
1E
1M
1U
1]
1d
0*
11
19
1A
1I
1Q
1Y
1a
b11111110 (
b0 %
0,
1#
#100
1&
0c
1e
0$
1b
1[
0\
1^
1Z
1S
0T
1V
1R
1K
0L
1N
1J
1C
0D
1F
1B
1;
0<
1>
1:
13
04
16
0-
1/
12
1*
b1111111 '
1+
b11111111 (
b0 %
0,
0.
0#
b11111111 "
#150
0:
0B
0J
0R
0Z
0b
0$
12
03
0;
0C
0K
0S
0[
0&
1.
b1 '
1+
14
06
0<
0>
0D
0F
0L
0N
0T
0V
0\
0^
0c
0e
1-
0/
05
0=
0E
0M
0U
0]
0d
0*
01
09
0A
0I
0Q
0Y
0a
b0 (
b10 %
0,
1#
#200
1&
1e
0$
1b
1[
1^
1Z
1S
1V
1R
1K
1N
1J
1C
1F
1B
1;
1>
1:
13
0-
1/
12
04
16
0<
0D
0L
0T
0\
0c
1*
b1111111 '
1+
15
1=
1E
1M
1U
1]
1d
b1 (
b0 %
0,
0.
10
18
1@
1H
1P
1X
1`
0#
b1 "
b11111111 !
#250
12
1.
b1111111 '
1+
14
06
1<
0>
1D
0F
1L
0N
1T
0V
1\
0^
1c
0e
1-
0/
05
17
0=
1?
0E
1G
0M
1O
0U
1W
0]
1_
0d
1f
0*
11
19
1A
1I
1Q
1Y
1a
b11111110 (
b11111110 %
0,
1#
#300
14
0-
1/
12
1*
b1111111 '
1+
b11111111 (
b11111110 %
0,
0.
0#
b11111111 "
#350
12
1:
1B
1J
1R
1Z
1b
0$
1.
1+
04
16
13
0<
1>
1;
0D
1F
1C
0L
1N
1K
0T
1V
1S
0\
1^
b1111111 '
1[
0c
1e
1&
1-
0/
15
07
1=
0?
1E
0G
1M
0O
1U
0W
1]
0_
1d
0f
0*
01
09
0A
0I
0Q
0Y
0a
b0 (
b0 %
0,
1#
#400
1b
1[
0\
1^
1Z
1S
0T
1V
1R
1K
0L
1N
1J
1C
0D
1F
1B
1;
0<
1>
1:
13
1$
04
16
0&
0-
1/
12
1c
0e
1*
b1111111 '
1+
0d
b1 (
b10000000 %
0,
0.
0`
0#
b1 "
b1111111 !
#450
0$
12
1&
1.
b1111111 '
1+
14
06
1<
0>
1D
0F
1L
0N
1T
0V
1\
0^
0c
1e
1-
0/
05
17
0=
1?
0E
1G
0M
1O
0U
1W
0]
1_
1d
0*
11
19
1A
1I
1Q
1Y
1a
b11111110 (
b1111110 %
0,
1#
#500
14
0-
1/
12
1*
b1111111 '
1+
b11111111 (
b1111110 %
0,
0.
0#
b11111111 "
#550
1$
12
1:
1B
1J
1R
1Z
1b
0&
1.
1+
04
16
13
0<
1>
1;
0D
1F
1C
0L
1N
1K
0T
1V
1S
0\
1^
b1111111 '
1[
1c
0e
1-
0/
15
07
1=
0?
1E
0G
1M
0O
1U
0W
1]
0_
0d
0*
01
09
0A
0I
0Q
0Y
0a
b0 (
b10000000 %
0,
1#
#600
0:
0B
0J
0R
0Z
0b
0$
03
0;
0C
0K
0S
0[
0&
0-
1/
12
14
06
0<
0>
0D
0F
0L
0N
0T
0V
0\
0^
1c
0e
1*
b1 '
1+
05
0=
0E
0M
0U
0]
1d
b1 (
b10000010 %
0,
0.
00
08
0@
0H
0P
0X
1`
0#
b1 "
b10000001 !
#650
1b
1[
1^
1Z
1S
1V
1R
1K
1N
1J
1C
1F
1B
1;
1>
1:
12
13
0$
1.
b1111111 '
1+
04
16
0<
0D
0L
0T
0\
1c
1&
1-
0/
15
1=
1E
1M
1U
1]
0d
1f
0*
11
19
1A
1I
1Q
1Y
1a
b11111110 (
b10000000 %
0,
1#
#700
1c
0$
1b
1[
0\
1^
1Z
1S
0T
1V
1R
1K
0L
1N
1J
1C
0D
1F
1B
1;
0<
1>
1:
13
04
16
0-
1/
12
1*
b1111111 '
1+
b11111111 (
b10000000 %
0,
0.
0#
b11111111 "
#750
0:
0B
0J
0R
0Z
0b
12
03
0;
0C
0K
0S
0[
0$
1.
b1 '
1+
14
06
0<
0>
0D
0F
0L
0N
0T
0V
0\
0^
1c
0e
0&
1-
0/
05
0=
0E
0M
0U
0]
1d
0f
0*
01
09
0A
0I
0Q
0Y
0a
b0 (
b10000010 %
0,
1#
#800
1$
1L
1T
1\
0c
1&
14
0-
1/
1M
1U
1]
0d
1f
12
1*
1I
1Q
1Y
1a
b1 '
1+
b11110001 (
b1110010 %
0,
0.
0#
b11110001 "
