andornot.v
//*******************************//
// Operations: and, or, not
// Op codes
// op == 00 -> and
// op == 01 -> or
// op == 10 -> not a
//*******************************//

module andornot( s, a, b, ctrl);
input [7:0] a; //var1
input [7:0] b; //var2
output reg [7:0] s;
output overflow; //indicates if there was an over flow
input [1:0] ctrl; //operation choice

always @(ctrl or a or b) begin
	case (ctrl)
		2'b00: s = a & b;
		2'b01: s = a | b;
		2'b10: s = ~a;
	endcase
end

endmodule

andornot_tb.v
`timescale 1ps/1ps

module andornot_tb;
reg signed [7:0] a;
reg signed [7:0] b;
reg [1:0] ctrl;
wire signed [7:0] s;

initial
	begin
		$dumpfile("andornot.vcd");
		$dumpvars(0,Johnson);
		$display("  a   b ctrl   s  overflow");
		$monitor("%d %d  %d  | %d  %d", a, b, ctrl, s, ctrl);
		
		//and
		#0  a = 8'b101	; b =  8'b000;  ctrl = 2'b00;
		#50 a = 8'b101	; b =  8'b001;  ctrl = 2'b00;
		#50 a = 8'b101	; b =  8'b010;  ctrl = 2'b00;
		#50 a = 8'b101	; b =  8'b100;  ctrl = 2'b00;
		#50 a = 8'b101	; b =  8'b100;  ctrl = 2'b00;
		#50 a = 8'b101	; b =  8'b101;  ctrl = 2'b00;
		#50 a = 8'b101	; b =  -8'b110;  ctrl = 2'b00;
		#50 a = 8'b101	; b =  -8'b111;  ctrl = 2'b00;
		
		//or
		#50  a = 8'b101	; b =  8'b000;   ctrl = 2'b01;
		#50 a = 8'b101	; b =  8'b001;   ctrl = 2'b01;
		#50 a = 8'b101	; b =  8'b010;   ctrl = 2'b01;
		#50 a = 8'b101	; b =  8'b100;   ctrl = 2'b01;
		#50 a = 8'b101	; b =  8'b100;   ctrl = 2'b01;
		#50 a = 8'b101	; b =  8'b101;   ctrl = 2'b01;
		#50 a = 8'b101	; b =  -8'b110;  ctrl = 2'b01;
		#50 a = 8'b101	; b =  -8'b111;  ctrl = 2'b01;
		
		//not
		#50  a = 8'b101	; b =  8'b000;   ctrl = 2'b10;
		#50 a = 8'b101	; b =  8'b001;   ctrl = 2'b10;
		#50 a = 8'b101	; b =  8'b010;   ctrl = 2'b10;
		#50 a = 8'b101	; b =  8'b100;   ctrl = 2'b10;
		#50 a = 8'b101	; b =  8'b100;   ctrl = 2'b10;
		#50 a = 8'b101	; b =  8'b101;   ctrl = 2'b10;
		#50 a = 8'b101	; b =  -8'b110;  ctrl = 2'b10;
		#50 a = 8'b101	; b =  -8'b111;  ctrl = 2'b10;
		
		#50 $finish;
	end

andornot Johnson( s, a, b, ctrl );

endmodule

andornot.vcd
$date
	Tue May 14 17:19:04 2019
$end
$version
	Icarus Verilog
$end
$timescale
	1ps
$end
$scope module andornot_tb $end
$scope module Johnson $end
$var wire 8 ! a [7:0] $end
$var wire 8 " b [7:0] $end
$var wire 2 # ctrl [1:0] $end
$var wire 1 $ overflow $end
$var reg 8 % s [7:0] $end
$upscope $end
$upscope $end
$enddefinitions $end
#0
$dumpvars
b0 %
z$
b0 #
b0 "
b101 !
$end
#50
b1 %
b1 "
#100
b0 %
b10 "
#150
b100 %
b100 "
#250
b101 %
b101 "
#300
b0 %
b11111010 "
#350
b1 %
b11111001 "
#400
b101 %
b1 #
b0 "
#450
b1 "
#500
b111 %
b10 "
#550
b101 %
b100 "
#650
b101 "
#700
b11111111 %
b11111010 "
#750
b11111101 %
b11111001 "
#800
b11111010 %
b10 #
b0 "
#850
b1 "
#900
b10 "
#950
b100 "
#1050
b101 "
#1100
b11111010 "
#1150
b11111001 "
