compare.v
//*******************************// 
// Ctrl codes
// ctrl == 0000 -> N/A
// ctrl == 0001 -> N/A
// ctrl == 0010 -> transfer A
// ctrl == 0011 -> increment A
// ctrl == 0100 -> Decrement A
// ctrl == 0101 -> 1's compliment
// ctrl == 0110 -> A NOR B
// ctrl == 0111 -> A XOR B
// ctrl == 1100 -> A XNOR B
// ctrl == 1101 -> A GT B (greater than)
// ctrl == 1110 -> A LT B (less than)
// ctrl == 1111 -> A EQ B (equal)
//*******************************//

module compare( s, a, b, ctrl );
input [7:0] a; //var1
input [7:0] b; //var2
output reg [7:0] s;
output overflow; //indicates if there was an over flow
input [3:0] ctrl; //operation choice

always @( ctrl or a or b ) begin
	case (ctrl)
		4'd2:  s = a;
		4'd3:  s = a + 1;
		4'd4:  s = a - 1;
		4'd5:
			if(a > 127)
				s = a - 1;
			else
				s = a;
		4'd6:  s = ~(a | b);
		4'd7:  s = a^b;
		4'd8:  s = a^~b;
		4'd9:  s = (a > b);
		4'd10: s = (a < b);
		4'd11: s = (a == b);
	endcase
end

endmodule

compare_tb.v
`timescale 1ps/1ps

module compare_tb;
reg signed [7:0] a;
reg signed [7:0] b;
reg unsigned [3:0] ctrl;
wire signed [7:0] s;

initial
	begin
		$dumpfile("compare.vcd");
		$dumpvars(0,Johnson);
		$display("   a    b  ctrl     s");
		$monitor("%d %d   %d | %d", a, b, ctrl, s);
		
		//transfer A
		#0  a = 8'b101	; b =  8'b000;  ctrl = 4'd2;
		#50 a = -8'b101	; b =  8'b001;  ctrl = 4'd2;
		#50 a = 8'b0	; b =  8'b010;  ctrl = 4'd2;
		#50 a = 8'd127	; b =  -8'b01;  ctrl = 4'd2;
		
		//increment A
		#50  a = 8'b101	; b =  8'b000;  ctrl = 4'd3;
		#50 a = -8'b101	; b =  8'b001;  ctrl = 4'd3;
		#50 a = 8'b0	; b =  8'b010;  ctrl = 4'd3;
		#50 a = 8'd127	; b =  -8'b01;  ctrl = 4'd3;
		
		//decrement A
		#50 a = 8'b101	; b =  8'b000;  ctrl = 4'd4;
		#50 a = -8'b101	; b =  8'b001;  ctrl = 4'd4;
		#50 a = 8'b0	; b =  8'b010;  ctrl = 4'd4;
		#50 a = 8'd127	; b =  -8'b01;  ctrl = 4'd4;
		
		//1's Compliment on A
		#50 a = 8'd5	; b =  8'b000;  ctrl = 4'd5;
		#50 a = -8'd5	; b =  8'b001;  ctrl = 4'd5;
		#50 a = 8'd127	; b =  8'b000;  ctrl = 4'd5;
		#50 a = -8'd128	; b =  8'b001;  ctrl = 4'd5;
		
		//A NOR B
		#50 a = 8'b101	; b =  8'b000;  ctrl = 4'd6;
		#50 a = -8'b101	; b =  8'b001;  ctrl = 4'd6;
		#50 a = 8'b0	; b =  8'b010;  ctrl = 4'd6;
		#50 a = 8'd127	; b =  -8'b01;  ctrl = 4'd6;
		
		//A XOR B
		#50 a = 8'b101	; b =  8'b000;  ctrl = 4'd7;
		#50 a = -8'b101	; b =  8'b001;  ctrl = 4'd7;
		#50 a = 8'b0	; b =  8'b010;  ctrl = 4'd7;
		#50 a = 8'd127	; b =  -8'b01;  ctrl = 4'd7;
		
		//A XNOR B
		#50 a = 8'b101	; b =  8'b000;  ctrl = 4'd8;
		#50 a = -8'b101	; b =  8'b001;  ctrl = 4'd8;
		#50 a = 8'b0	; b =  8'b010;  ctrl = 4'd8;
		#50 a = 8'd127	; b =  -8'b01;  ctrl = 4'd8;
		
		//A GT B
		#50 a = 8'b101	; b =  8'b000;  ctrl = 4'd9;
		#50 a = -8'b101	; b =  8'b001;  ctrl = 4'd9;
		#50 a = 8'b0	; b =  8'b010;  ctrl = 4'd9;
		#50 a = 8'd127	; b =  -8'b01;  ctrl = 4'd9;
		
		//A LT B
		#50 a = 8'b101	; b =  8'b000;  ctrl = 4'd10;
		#50 a = -8'b101	; b =  8'b001;  ctrl = 4'd10;
		#50 a = 8'b0	; b =  8'b010;  ctrl = 4'd10;
		#50 a = 8'd127	; b =  -8'b01;  ctrl = 4'd10;
		
		//A EQ B
		#50 a = 8'b101	; b =  8'b101;  ctrl = 4'd11;
		#50 a = -8'b101	; b =  -8'b101;  ctrl = 4'd11;
		#50 a = 8'b0	; b =  8'b010;  ctrl = 4'd11;
		#50 a = 8'd127	; b =  -8'b01;  ctrl = 4'd11;
		
		#50 $finish;
	end

compare Johnson( s, a, b, ctrl );

endmodule

compare.vcd
$date
	Tue May 14 19:45:31 2019
$end
$version
	Icarus Verilog
$end
$timescale
	1ps
$end
$scope module compare_tb $end
$scope module Johnson $end
$var wire 8 ! a [7:0] $end
$var wire 8 " b [7:0] $end
$var wire 4 # ctrl [3:0] $end
$var wire 1 $ overflow $end
$var reg 8 % s [7:0] $end
$upscope $end
$upscope $end
$enddefinitions $end
#0
$dumpvars
b101 %
z$
b10 #
b0 "
b101 !
$end
#50
b11111011 %
b1 "
b11111011 !
#100
b0 %
b10 "
b0 !
#150
b1111111 %
b11111111 "
b1111111 !
#200
b110 %
b11 #
b0 "
b101 !
#250
b11111100 %
b1 "
b11111011 !
#300
b1 %
b10 "
b0 !
#350
b10000000 %
b11111111 "
b1111111 !
#400
b100 %
b100 #
b0 "
b101 !
#450
b11111010 %
b1 "
b11111011 !
#500
b11111111 %
b10 "
b0 !
#550
b1111110 %
b11111111 "
b1111111 !
#600
b101 %
b101 #
b0 "
b101 !
#650
b11111010 %
b1 "
b11111011 !
#700
b1111111 %
b0 "
b1111111 !
#750
b1 "
b10000000 !
#800
b11111010 %
b110 #
b0 "
b101 !
#850
b100 %
b1 "
b11111011 !
#900
b11111101 %
b10 "
b0 !
#950
b0 %
b11111111 "
b1111111 !
#1000
b101 %
b111 #
b0 "
b101 !
#1050
b11111010 %
b1 "
b11111011 !
#1100
b10 %
b10 "
b0 !
#1150
b10000000 %
b11111111 "
b1111111 !
#1200
b11111010 %
b1000 #
b0 "
b101 !
#1250
b101 %
b1 "
b11111011 !
#1300
b11111101 %
b10 "
b0 !
#1350
b1111111 %
b11111111 "
b1111111 !
#1400
b1 %
b1001 #
b0 "
b101 !
#1450
b1 "
b11111011 !
#1500
b0 %
b10 "
b0 !
#1550
b11111111 "
b1111111 !
#1600
b1010 #
b0 "
b101 !
#1650
b1 "
b11111011 !
#1700
b1 %
b10 "
b0 !
#1750
b11111111 "
b1111111 !
#1800
b1011 #
b101 "
b101 !
#1850
b11111011 "
b11111011 !
#1900
b0 %
b10 "
b0 !
#1950
b11111111 "
b1111111 !
