accumulator.v
//Accumulator by Ryan Thompson

module accumulator(s, a, clk);

input clk;
input [7:0] a;
output reg [7:0] s;

always @( negedge clk ) begin
		s <= a;
end

endmodule

mux.v
//Module by Ryan Thompson
//Muliplexer for the 8bit Power ALU

/*
ctrl operations for this mux
00	passes the compare module's results
01	passes the andornot module's results
10	passes the addsub module's results
*/

module mux( s, ctrl, compare_in, andornot_in, addsub_in, overflow);

output reg [7:0] s; //output
input [1:0] ctrl;	//picks which module's output to pass
input [7:0] compare_in; 	//
input [7:0] andornot_in;	//Outputs of ALU modules -> mux
input [7:0] addsub_in;		//
input overflow; //accounts for arethmetic overflow from add

initial begin
	s = 0;
end

always @( ctrl or compare_in or andornot_in or addsub_in or overflow) begin
	case(ctrl) 
	2'b00:   s <= compare_in;
	2'b01:   s <= andornot_in;
	2'b10:   s <= addsub_in;
	default: s <= 0;
	endcase
end

endmodule

control.v
//Control module for the 8bitPowerALU by Ryan Thompson
module control(opcode, compare_ctrl, andornot_ctrl, addsub_ctrl, mux_ctrl, clk);

output reg [3:0] compare_ctrl;
output reg [1:0] andornot_ctrl;
output reg       addsub_ctrl;
output reg [1:0] mux_ctrl;
input [3:0] opcode;
input clk;

//No-op codes for the respective modules
//That being said, it doesn't really matter;
// The multiplexer will assign the appropriate output
initial begin
	compare_ctrl  = 0;
	andornot_ctrl = 2'b11;
	addsub_ctrl   = 0;
	mux_ctrl      = 0;
end

//opcode -> operation
always @( clk ) begin
	
    //math opcode conversion
	case(opcode)
	4'b0000: compare_ctrl  <= 4'b0010; 
	4'b0001: compare_ctrl  <= 4'b0011;  
	4'b0010: addsub_ctrl   <= 0;        
	4'b0011: addsub_ctrl   <= 1;        
	4'b0100: compare_ctrl  <= 4'b0100;  
	4'b0101: compare_ctrl  <= 4'b0101;  
	4'b0110: andornot_ctrl <= 2'b00;   
	4'b0111: andornot_ctrl <= 2'b11;   
	4'b1000: andornot_ctrl <= 2'b01;   
	4'b1001: compare_ctrl  <= 4'b0110;  
	4'b1010: compare_ctrl  <= 4'b0111;  
	4'b1011: compare_ctrl  <= 4'b1100;  
	4'b1100: compare_ctrl  <= 4'b1101;  
	4'b1101: compare_ctrl  <= 4'b1110;  
	4'b1110: compare_ctrl  <= 4'b1111;  
	4'b1111: andornot_ctrl <= 2'b10;   
	endcase
	
	//mux opcode conversion
	case(opcode)
	4'b0000: mux_ctrl <= 2'b00;
	4'b0001: mux_ctrl <= 2'b00;
	4'b0010: mux_ctrl <= 2'b10;
	4'b0011: mux_ctrl <= 2'b10;
	4'b0100: mux_ctrl <= 2'b00;
	4'b0101: mux_ctrl <= 2'b00;
	4'b0110: mux_ctrl <= 2'b01;
	4'b0111: mux_ctrl <= 2'b01;
	4'b1000: mux_ctrl <= 2'b01;
	4'b1001: mux_ctrl <= 2'b00;
	4'b1010: mux_ctrl <= 2'b00;
	4'b1011: mux_ctrl <= 2'b00;
	4'b1100: mux_ctrl <= 2'b00;
	4'b1101: mux_ctrl <= 2'b00;
	4'b1110: mux_ctrl <= 2'b00;
	4'b1111: mux_ctrl <= 2'b01;
	endcase
end

endmodule

full_adder.v
module full_adder(s, cout, a, b, cin);

input a,b,cin;
output s,cout;
wire w1, w2, w3;

//Both Circuits
xor(w1, a, b);

// Summation circuit
xor(s, w1, cin);

// carry-out circuit
or(cout, w2, w3);
and(w2, w1, cin);
and(w3, a, b);

endmodule

adder_subtractor.v
//Module by Ryan Thompson
//https://tinyurl.com/y435nrgr
module adder_subtractor( s, overflow, a, b, op);
input  signed [7:0] a; //var1
input  signed [7:0] b; //var2
output signed [7:0] s; //output
output overflow; //indicates if there was an over flow
input  op;      // 0 -> a+b, 1 -> a-b

//Carry and xor wires
wire [6:0] carry;
wire [7:0] bxor; //wires connecting to the FAs
wire last_cout;

//xor chain for subtraction (take a look at the diagram)
xor(bxor[0], b[0], op);
xor(bxor[1], b[1], op);
xor(bxor[2], b[2], op);
xor(bxor[3], b[3], op);
xor(bxor[4], b[4], op);
xor(bxor[5], b[5], op);
xor(bxor[6], b[6], op);
xor(bxor[7], b[7], op);

//The cascaded full adders
full_adder a0(s[0], carry[0], a[0], bxor[0], op);
full_adder a1(s[1], carry[1], a[1], bxor[1], carry[0]);
full_adder a2(s[2], carry[2], a[2], bxor[2], carry[1]);
full_adder a3(s[3], carry[3], a[3], bxor[3], carry[2]);
full_adder a4(s[4], carry[4], a[4], bxor[4], carry[3]);
full_adder a5(s[5], carry[5], a[5], bxor[5], carry[4]);
full_adder a6(s[6], carry[6], a[6], bxor[6], carry[5]);
full_adder a7(s[7], last_cout,a[7], bxor[7], carry[6]);

//xor that manages overflow
xor(overflow, carry[6], last_cout);

endmodule

andornot.v
//*******************************//
//Performs AND, OR, and NOT operations on
//two 8bit inputs
//by Ryan Thompson
// Operations: and, or, not
// Op codes
// op == 00 -> and
// op == 01 -> or
// op == 10 -> not a
// op == 11 -> nand
//*******************************//

module andornot( s, a, b, ctrl);
input [7:0] a; 		//Input1
input [7:0] b; 		//Input2
input [1:0] ctrl; 	//operation choice
output reg [7:0] s; //output

initial begin
	s = 0;
end

always @( ctrl or a or b ) begin
	case (ctrl)
		2'b00: s = a & b;
		2'b01: s = a | b;
		2'b10: s = ~a;
		2'b11: s = (a & b);
		default: s = 0;
	endcase
end

endmodule

compare.v
//*******************************// 
// Ctrl codes
// ctrl == 0000 -> N/A
// ctrl == 0001 -> N/A
// ctrl == 0010 -> transfer A
// ctrl == 0011 -> increment A
// ctrl == 0100 -> Decrement A
// ctrl == 0101 -> 1's compliment
// ctrl == 0110 -> A NOR B
// ctrl == 0111 -> A XOR B
// ctrl == 1100 -> A XNOR B
// ctrl == 1101 -> A GT B (greater than)
// ctrl == 1110 -> A LT B (less than)
// ctrl == 1111 -> A EQ B (equal)
//*******************************//

module compare( s, a, b, ctrl );
input signed [7:0] a; //var1
input signed [7:0] b; //var2
output reg   [7:0] s;
output overflow; //indicates if there was an over flow
input [3:0] ctrl; //operation choice

always @( ctrl or a or b) begin
	case (ctrl)
		4'd2:  s = a;
		4'd3:  s = a + 1;
		4'd4:  s = a - 1;
		4'd5:
			if(a > 127)
				s = a - 1;
			else
				s = a;
		4'd6:  s = ~(a | b);
		4'd7:  s = a^b;
		4'd8:  s = a^~b;
		4'd9:  s = (a > b);
		4'd10: s = (a < b);
		4'd11: s = (a == b);
		default: s = 0;
	endcase
end

endmodule

PowerALU_Ryan_Thompson.v
//Module by Ryan Thompson
module PowerALU( b, opcode, a, clk);

//input/output variables
output [7:0] b;
input  [3:0] opcode;
input  [7:0] a;
input clk;

//internal registers and wires
wire [3:0] compare_ctrl;
wire [1:0] andornot_ctrl;
wire       addsub_ctrl;
wire [1:0] mux_ctrl;

//math components to mux wires
wire [7:0] compare2mux;
wire [7:0] andornot2mux;
wire [7:0] addsub2mux;
wire overflow;
wire [7:0] mux2accu;


//Math modules
compare alu_compare( compare2mux, a, b, compare_ctrl );
andornot alu_andornot( andornot2mux, a, b, andornot_ctrl );
adder_subtractor alu_addsub( addsub2mux, overflow, a, b, addsub_ctrl );

control alu_control( opcode, compare_ctrl, andornot_ctrl, addsub_ctrl, mux_ctrl, clk);
mux alu_mux( mux2accu, mux_ctrl, compare2mux, andornot2mux, addsub2mux, overflow );
accumulator alu_accu(b, mux2accu, clk);
endmodule

PowerALU_Ryan_Thompson_tb.v
`timescale 1ps/1ps

module PowerALU_tb;
wire signed [7:0] b;
reg [3:0] opcode;
reg signed [7:0] a;
reg [32:0] i;
reg clk;

initial begin
for(i = 0; i < 40; i++) begin
	#25 clk = ~clk;
	end
$finish;
end

initial begin
	$dumpfile("PowerALU.vcd");
	$dumpvars(0,DUT);
	//$display("a  b cin   s cout");
	//$monitor("%b  %b  %b  | %b  %b", a, b, cin, s, cout);
	
	opcode <= 0;
	a      <= 0;
	i      <= 0;
	clk    <= 0;
	
	//Transfer A
	#13 opcode <= 4'b0000;	a <= 8'd10;
	#50 opcode <= 4'b0000;	a <= 8'd20;
	#50 opcode <= 4'b0000;	a <= -8'd15;
	
	//Increment A
	#50 opcode <= 4'b0001;	a <= -8'd15;
	#50 opcode <= 4'b0001;	a <= 8'd10;
	#50 opcode <= 4'b0001;	a <= 8'd20;
	#50 opcode <= 4'b0001;	a <= 8'd127;
	
	//A ADD B
	#50 opcode <= 4'b0010;	a <= -8'd15;
	#50 opcode <= 4'b0010;	a <= 8'd10;
	#50 opcode <= 4'b0010;	a <= 8'd20;
	#50 opcode <= 4'b0010;	a <= 8'd127;
	#50 opcode <= 4'b0010;	a <= -8'd5;
	
	//A SUB B
	#200 opcode <= 4'b0011;	a <= -8'd5;
	#50 opcode <= 4'b0011;	a <= 8'd10;
	#50 opcode <= 4'b0011;	a <= 8'd20;
	#50 opcode <= 4'b0011;	a <= 8'd127;
	#50 opcode <= 4'b0011;	a <= -8'd5;
end

PowerALU DUT(b, opcode, a, clk);

endmodule

PowerALU.vcd
$date
	Sat May 18 03:51:59 2019
$end
$version
	Icarus Verilog
$end
$timescale
	1ps
$end
$scope module PowerALU_tb $end
$scope module DUT $end
$var wire 8 ! a [7:0] $end
$var wire 1 " clk $end
$var wire 4 # opcode [3:0] $end
$var wire 1 $ overflow $end
$var wire 2 % mux_ctrl [1:0] $end
$var wire 8 & mux2accu [7:0] $end
$var wire 4 ' compare_ctrl [3:0] $end
$var wire 8 ( compare2mux [7:0] $end
$var wire 8 ) b [7:0] $end
$var wire 2 * andornot_ctrl [1:0] $end
$var wire 8 + andornot2mux [7:0] $end
$var wire 1 , addsub_ctrl $end
$var wire 8 - addsub2mux [7:0] $end
$scope module alu_accu $end
$var wire 1 " clk $end
$var wire 8 . a [7:0] $end
$var reg 8 / s [7:0] $end
$upscope $end
$scope module alu_addsub $end
$var wire 8 0 a [7:0] $end
$var wire 8 1 b [7:0] $end
$var wire 1 $ overflow $end
$var wire 8 2 s [7:0] $end
$var wire 1 , op $end
$var wire 1 3 last_cout $end
$var wire 7 4 carry [6:0] $end
$var wire 8 5 bxor [7:0] $end
$scope module a0 $end
$var wire 1 6 a $end
$var wire 1 7 b $end
$var wire 1 8 cout $end
$var wire 1 9 s $end
$var wire 1 : w1 $end
$var wire 1 ; w2 $end
$var wire 1 < w3 $end
$var wire 1 , cin $end
$upscope $end
$scope module a1 $end
$var wire 1 = a $end
$var wire 1 > b $end
$var wire 1 ? cin $end
$var wire 1 @ cout $end
$var wire 1 A s $end
$var wire 1 B w1 $end
$var wire 1 C w2 $end
$var wire 1 D w3 $end
$upscope $end
$scope module a2 $end
$var wire 1 E a $end
$var wire 1 F b $end
$var wire 1 G cin $end
$var wire 1 H cout $end
$var wire 1 I s $end
$var wire 1 J w1 $end
$var wire 1 K w2 $end
$var wire 1 L w3 $end
$upscope $end
$scope module a3 $end
$var wire 1 M a $end
$var wire 1 N b $end
$var wire 1 O cin $end
$var wire 1 P cout $end
$var wire 1 Q s $end
$var wire 1 R w1 $end
$var wire 1 S w2 $end
$var wire 1 T w3 $end
$upscope $end
$scope module a4 $end
$var wire 1 U a $end
$var wire 1 V b $end
$var wire 1 W cin $end
$var wire 1 X cout $end
$var wire 1 Y s $end
$var wire 1 Z w1 $end
$var wire 1 [ w2 $end
$var wire 1 \ w3 $end
$upscope $end
$scope module a5 $end
$var wire 1 ] a $end
$var wire 1 ^ b $end
$var wire 1 _ cin $end
$var wire 1 ` cout $end
$var wire 1 a s $end
$var wire 1 b w1 $end
$var wire 1 c w2 $end
$var wire 1 d w3 $end
$upscope $end
$scope module a6 $end
$var wire 1 e a $end
$var wire 1 f b $end
$var wire 1 g cin $end
$var wire 1 h cout $end
$var wire 1 i s $end
$var wire 1 j w1 $end
$var wire 1 k w2 $end
$var wire 1 l w3 $end
$upscope $end
$scope module a7 $end
$var wire 1 m a $end
$var wire 1 n b $end
$var wire 1 o cin $end
$var wire 1 3 cout $end
$var wire 1 p s $end
$var wire 1 q w1 $end
$var wire 1 r w2 $end
$var wire 1 s w3 $end
$upscope $end
$upscope $end
$scope module alu_andornot $end
$var wire 8 t a [7:0] $end
$var wire 8 u b [7:0] $end
$var wire 2 v ctrl [1:0] $end
$var reg 8 w s [7:0] $end
$upscope $end
$scope module alu_compare $end
$var wire 8 x a [7:0] $end
$var wire 8 y b [7:0] $end
$var wire 1 z overflow $end
$var wire 4 { ctrl [3:0] $end
$var reg 8 | s [7:0] $end
$upscope $end
$scope module alu_control $end
$var wire 1 " clk $end
$var wire 4 } opcode [3:0] $end
$var reg 1 , addsub_ctrl $end
$var reg 2 ~ andornot_ctrl [1:0] $end
$var reg 4 !" compare_ctrl [3:0] $end
$var reg 2 "" mux_ctrl [1:0] $end
$upscope $end
$scope module alu_mux $end
$var wire 8 #" addsub_in [7:0] $end
$var wire 8 $" andornot_in [7:0] $end
$var wire 8 %" compare_in [7:0] $end
$var wire 2 &" ctrl [1:0] $end
$var wire 1 $ overflow $end
$var reg 8 '" s [7:0] $end
$upscope $end
$upscope $end
$upscope $end
$enddefinitions $end
#0
$dumpvars
b0 '"
b0 &"
b0 %"
b0 $"
b0 #"
b0 ""
b10 !"
b11 ~
b0 }
b0 |
b10 {
zz
b0 y
b0 x
b0 w
b11 v
b0 u
b0 t
0s
0r
0q
0p
0o
0n
0m
0l
0k
0j
0i
0h
0g
0f
0e
0d
0c
0b
0a
0`
0_
0^
0]
0\
0[
0Z
0Y
0X
0W
0V
0U
0T
0S
0R
0Q
0P
0O
0N
0M
0L
0K
0J
0I
0H
0G
0F
0E
0D
0C
0B
0A
0@
0?
0>
0=
0<
0;
0:
09
08
07
06
b0 5
b0 4
03
b0 2
b0 1
b0 0
b0 /
b0 .
b0 -
0,
b0 +
b11 *
b0 )
b0 (
b10 '
b0 &
b0 %
0$
b0 #
0"
b0 !
$end
#13
b1010 &
b1010 .
b1010 '"
1A
b1010 -
b1010 2
b1010 #"
1Q
1B
1R
1=
1M
b1010 (
b1010 |
b1010 %"
b1010 !
b1010 0
b1010 t
b1010 x
#25
1"
#50
1I
1Y
1G
1W
0A
1@
b10100 -
b10100 2
b10100 #"
0Q
b1010 4
1P
0B
1D
0R
1T
1>
1N
b1010 5
b1010 +
b1010 w
b1010 $"
b1010 )
b1010 /
b1010 1
b1010 u
b1010 y
0"
#63
b10100 &
b10100 .
b10100 '"
0S
0a
0O
0_
0G
0H
0W
0X
1A
0@
1I
0K
1Q
b0 4
0P
b11110 -
b11110 2
b11110 #"
1Y
0[
1B
0D
1J
1R
0T
1Z
0=
1E
0M
1U
b0 +
b0 w
b0 $"
b10100 (
b10100 |
b10100 %"
b10100 !
b10100 0
b10100 t
b10100 x
#75
1"
#100
1a
1O
1_
0A
0I
1H
1Q
b101000 -
b101000 2
b101000 #"
0Y
b10100 4
1X
0B
0J
1L
0R
0Z
1\
0>
1F
0N
1V
b10100 5
b10100 +
b10100 w
b10100 $"
b10100 )
b10100 /
b10100 1
b10100 u
b10100 y
0"
#113
b11110001 &
b11110001 .
b11110001 '"
13
1r
0$
1o
1h
1k
0Q
1g
0O
1`
19
1I
b1110000 4
0H
0a
1c
0i
b101 -
b101 2
b101 #"
0p
1:
1J
0L
1b
1j
1q
16
0E
1]
1e
1m
b10000 +
b10000 w
b10000 $"
b11110001 (
b11110001 |
b11110001 %"
b11110001 !
b11110001 0
b11110001 t
b11110001 x
#125
1"
#150
1A
1?
09
b1110001 4
18
0I
1a
0c
1i
0k
b11100010 -
b11100010 2
b11100010 #"
1p
0r
0:
1<
0J
0b
1d
0j
1l
0q
1s
17
0F
1^
1f
1n
b11110001 5
b11110001 +
b11110001 w
b11110001 $"
b11110001 )
b11110001 /
b11110001 1
b11110001 u
b11110001 y
0"
#163
b1 #
b1 }
#175
b11110010 &
b11110010 .
b11110010 '"
b11110010 (
b11110010 |
b11110010 %"
b11 '
b11 {
b11 !"
1"
#200
0I
0G
0?
0@
19
b1110000 4
08
b11100011 -
b11100011 2
b11100011 #"
1A
0C
1:
0<
1B
07
1>
b11110010 5
b11110000 +
b11110000 w
b11110000 $"
b11110010 )
b11110010 /
b11110010 1
b11110010 u
b11110010 y
0"
#213
b1011 &
b1011 .
b1011 '"
1I
1G
0_
0g
0o
0$
09
0A
1@
1Q
1Y
0X
1a
0c
0`
1i
0k
b10 4
0h
b11111100 -
b11111100 2
b11111100 #"
1p
0r
03
0:
0B
1D
1R
1Z
0\
1b
0d
1j
0l
1q
0s
06
1=
1M
0U
0]
0e
0m
b10 +
b10 w
b10 $"
b1011 (
b1011 |
b1011 %"
b1010 !
b1010 0
b1010 t
b1010 x
#225
1"
#250
1W
19
0Q
b1010 4
1P
1Y
0a
0i
b10101 -
b10101 2
b10101 #"
0p
1:
0R
1T
0Z
0b
0j
0q
17
1N
0V
0^
0f
0n
b1011 5
b1010 +
b1010 w
b1010 $"
b1011 )
b1011 /
b1011 1
b1011 u
b1011 y
0"
#263
b10101 &
b10101 .
b10101 '"
0S
0a
0O
0_
0G
0H
0W
0X
1A
0@
1I
0K
1Q
b0 4
0P
b11111 -
b11111 2
b11111 #"
1Y
0[
1B
0D
1J
1R
0T
1Z
0=
1E
0M
1U
b0 +
b0 w
b0 $"
b10101 (
b10101 |
b10101 %"
b10100 !
b10100 0
b10100 t
b10100 x
#275
1"
#300
1a
1O
1_
0A
0I
1H
1Q
b101001 -
b101001 2
b101001 #"
0Y
b10100 4
1X
0B
0J
1L
0R
0Z
1\
0>
1F
0N
1V
b10101 5
b10100 +
b10100 w
b10100 $"
b10101 )
b10101 /
b10101 1
b10101 u
b10101 y
0"
#313
b10000000 &
b10000000 .
b10000000 '"
1p
1$
1I
1o
1G
1h
1@
1Y
1k
1C
1W
1g
1?
1P
1`
09
b1111111 4
18
0A
0Q
1S
0a
1c
b10010100 -
b10010100 2
b10010100 #"
0i
0:
1<
1B
1R
1b
1j
16
1=
1M
1]
1e
b10101 +
b10101 w
b10101 $"
b10000000 (
b10000000 |
b10000000 %"
b1111111 !
b1111111 0
b1111111 t
b1111111 x
#325
1"
#350
0o
0h
1i
0k
0G
0W
0g
0@
0P
0`
1A
0C
1Q
0S
1a
0c
0$
0?
0O
0_
03
19
08
1I
0K
0H
1Y
0[
b0 4
0X
b11111111 -
b11111111 2
b11111111 #"
1p
0r
1:
0<
1J
0L
1Z
0\
1q
07
0F
0V
1n
b10000000 5
b0 +
b0 w
b0 $"
b10000000 )
b10000000 /
b10000000 1
b10000000 u
b10000000 y
0"
#363
b11110010 &
b11110010 .
b11110010 '"
1$
0A
0I
0Q
b1110001 -
b1110001 2
b1110001 #"
0p
13
0B
0J
0R
0q
1s
0=
0E
0M
1m
b10000000 +
b10000000 w
b10000000 $"
b11110010 (
b11110010 |
b11110010 %"
b11110001 !
b11110001 0
b11110001 t
b11110001 x
b10 #
b10 }
#375
b1110001 &
b1110001 .
b1110001 '"
b10 %
b10 ""
b10 &"
1"
#400
b1100010 &
b1100010 .
b1100010 '"
1A
1r
1?
1_
1g
1o
0$
09
18
0Y
1X
1a
1`
1i
b1110001 4
1h
b1100010 -
b1100010 2
b1100010 #"
0p
13
0:
1<
0Z
1\
0b
1d
0j
1l
1q
0s
17
1V
1^
1f
0n
b1110001 5
b1110001 +
b1110001 w
b1110001 $"
b1110001 )
b1110001 /
b1110001 1
b1110001 u
b1110001 y
0"
#413
b1111011 &
b1111011 .
b1111011 '"
0I
0$
0G
0?
0@
0_
0g
0o
03
19
08
1A
0C
1Q
1Y
0X
1a
0c
0`
1i
0k
b0 4
0h
b1111011 -
b1111011 2
b1111011 #"
0p
0r
1:
0<
1B
1R
1Z
0\
1b
0d
1j
0l
0q
06
1=
1M
0U
0]
0e
0m
b0 +
b0 w
b0 $"
b1011 (
b1011 |
b1011 %"
b1010 !
b1010 0
b1010 t
b1010 x
#425
1"
#450
b10000101 &
b10000101 .
b10000101 '"
1p
1$
1o
1h
0i
1k
1g
1`
0a
1c
1_
1X
1I
0Y
1[
1G
1W
0A
1@
b10000101 -
b10000101 2
b10000101 #"
0Q
b1111010 4
1P
0B
1D
0R
1T
1>
1N
b1111011 5
b1010 +
b1010 w
b1010 $"
b1111011 )
b1111011 /
b1111011 1
b1111011 u
b1111011 y
0"
#463
b10001111 &
b10001111 .
b10001111 '"
0S
0O
0G
0H
0W
1A
0@
1I
0K
1Q
b1110000 4
0P
b10001111 -
b10001111 2
b10001111 #"
0Y
0[
1B
0D
1J
1R
0T
0Z
1\
0=
1E
0M
1U
b10000 +
b10000 w
b10000 $"
b10101 (
b10101 |
b10101 %"
b10100 !
b10100 0
b10100 t
b10100 x
#475
1"
#500
b10100011 &
b10100011 .
b10100011 '"
1[
1W
1P
0Q
1S
0g
0o
0$
1O
1_
0`
0h
03
0I
1H
0Y
b11100 4
1X
1a
0c
0i
0k
b10100011 -
b10100011 2
b10100011 #"
1p
0r
0J
1L
1Z
0\
0b
0j
1q
1F
0V
0^
0f
1n
b10001111 5
b100 +
b100 w
b100 $"
b10001111 )
b10001111 /
b10001111 1
b10001111 u
b10001111 y
0"
#513
b1110 &
b1110 .
b1110 '"
13
0p
1r
0$
1o
1h
1k
1I
1g
1?
1G
1`
09
18
1A
b1111111 4
1@
1Q
0S
0a
1c
b1110 -
b1110 2
b1110 #"
0i
0:
1<
0B
1D
0R
1T
1b
1j
16
1=
1M
1]
1e
b1111 +
b1111 w
b1111 $"
b10000000 (
b10000000 |
b10000000 %"
b1111111 !
b1111111 0
b1111111 t
b1111111 x
#525
1"
#550
b10001101 &
b10001101 .
b10001101 '"
0A
1$
0?
03
19
b1111110 4
08
b10001101 -
b10001101 2
b10001101 #"
1p
0r
1:
0<
0q
07
0n
b1110 5
b1110 +
b1110 w
b1110 $"
b1110 )
b1110 /
b1110 1
b1110 u
b1110 y
0"
#563
b1001 &
b1001 .
b1001 '"
1Q
0$
1O
13
0I
1K
b1111110 4
1H
b1001 -
b1001 2
b1001 #"
0p
1r
1J
0L
1q
0E
1m
b1010 +
b1010 w
b1010 $"
b11111100 (
b11111100 |
b11111100 %"
b11111011 !
b11111011 0
b11111011 t
b11111011 x
#575
1"
#600
b100 &
b100 .
b100 '"
0Q
1C
0O
1?
1G
0H
09
18
0A
b1111011 4
1@
b100 -
b100 2
b100 #"
1I
0K
0:
1<
1B
0D
0J
17
0>
0F
b1001 5
b1001 +
b1001 w
b1001 $"
b1001 )
b1001 /
b1001 1
b1001 u
b1001 y
0"
#625
1"
#650
b11111111 &
b11111111 .
b11111111 '"
03
1p
0r
0$
0o
0h
1i
0k
0g
0`
1a
0c
0G
0_
0@
0S
0X
1A
0C
0O
1Y
0[
0?
0H
0W
19
08
1I
0K
b11111111 -
b11111111 2
b11111111 #"
1Q
b0 4
0P
1:
0<
1J
1R
0T
07
1F
0N
b100 5
b0 +
b0 w
b0 $"
b100 )
b100 /
b100 1
b100 u
b100 y
0"
#675
1"
#700
b11111010 &
b11111010 .
b11111010 '"
1O
1H
0I
1K
1?
1G
1W
1_
1g
1o
0$
09
18
1A
1@
1Q
1P
1Y
1X
1a
1`
1i
b1111111 4
1h
b11111010 -
b11111010 2
b11111010 #"
1p
13
0:
1<
0B
1D
0R
1T
0Z
1\
0b
1d
0j
1l
0q
1s
17
1>
1N
1V
1^
1f
1n
b11111111 5
b11111011 +
b11111011 w
b11111011 $"
b11111111 )
b11111111 /
b11111111 1
b11111111 u
b11111111 y
0"
#725
1"
#750
b11110101 &
b11110101 .
b11110101 '"
0Q
0A
0O
0?
0H
19
b1111010 4
08
b11110101 -
b11110101 2
b11110101 #"
1I
0K
1:
0<
0J
07
0F
b11111010 5
b11111010 +
b11111010 w
b11111010 $"
b11111010 )
b11111010 /
b11111010 1
b11111010 u
b11111010 y
0"
#763
b11 #
b11 }
#775
b1 &
b1 .
b1 '"
0$
1S
1O
1o
1g
1_
1W
1H
1G
0p
1r
13
0i
1k
1h
0a
1c
1`
0Y
1[
1X
0Q
1P
0I
1K
1C
1@
1?
1q
0s
1j
0l
1b
0d
1Z
0\
1R
0T
1J
1B
0D
0:
1<
b1111111 4
18
0n
0f
0^
0V
0N
1F
0>
17
0;
b1 -
b1 2
b1 #"
19
b101 5
1,
1"
#800
b11111010 &
b11111010 .
b11111010 '"
1?
09
1;
b1111111 4
18
1A
0C
1Q
0S
1Y
0[
1a
0c
1i
0k
b11111010 -
b11111010 2
b11111010 #"
1p
0r
1:
0<
0B
1D
0R
1T
0Z
1\
0b
1d
0j
1l
0q
1s
07
1>
1N
1V
1^
1f
1n
b11111110 5
b1 +
b1 w
b1 $"
b1 )
b1 /
b1 1
b1 u
b1 y
0"
#813
b1001 &
b1001 .
b1001 '"
0A
0?
08
1_
1g
1o
0$
19
0;
0Y
1[
1X
0a
1c
1`
0i
1k
b1111110 4
1h
b1001 -
b1001 2
b1001 #"
0p
1r
13
0:
1Z
0\
1b
0d
1j
0l
1q
0s
06
0U
0]
0e
0m
b0 +
b0 w
b0 $"
b1011 (
b1011 |
b1011 %"
b1010 !
b1010 0
b1010 t
b1010 x
#825
1"
#850
b1 &
b1 .
b1 '"
13
0p
1r
0$
1o
1h
0i
1k
1g
1`
0a
1c
1_
1X
0Y
1[
1W
b1 -
b1 2
b1 #"
0Q
1S
b1111110 4
1P
1R
0T
0N
b11110110 5
b1000 +
b1000 w
b1000 $"
b1001 )
b1001 /
b1001 1
b1001 u
b1001 y
0"
#863
b1011 &
b1011 .
b1011 '"
0W
0G
0P
1A
b1110100 4
0@
0I
0K
1Q
0S
b1011 -
b1011 2
b1011 #"
0Y
0[
1B
0D
0J
1L
0R
0Z
1\
0=
1E
0M
1U
b0 +
b0 w
b0 $"
b10101 (
b10101 |
b10101 %"
b10100 !
b10100 0
b10100 t
b10100 x
#875
1"
#900
b1001 &
b1001 .
b1001 '"
b1001 -
b1001 2
b1001 #"
0A
0B
0>
b11110100 5
b1011 )
b1011 /
b1011 1
b1011 u
b1011 y
0"
#913
b1110100 &
b1110100 .
b1110100 '"
1I
1G
1@
1C
1Y
1?
1W
18
b1111111 4
1P
09
1;
0A
0Q
1S
1a
0c
b1110100 -
b1110100 2
b1110100 #"
1i
0k
1:
1B
1R
0b
1d
0j
1l
16
1=
1M
1]
1e
b1011 +
b1011 w
b1011 $"
b10000000 (
b10000000 |
b10000000 %"
b1111111 !
b1111111 0
b1111111 t
b1111111 x
#925
1"
#950
b1011 &
b1011 .
b1011 '"
13
0p
1r
0$
1O
1_
1g
1o
19
0;
1A
0C
0I
1K
1H
1Q
0S
0Y
1[
1X
0a
1c
1`
b1011 -
b1011 2
b1011 #"
0i
1k
b1111111 4
1h
0:
1<
0B
1D
1J
0L
0R
1T
1Z
0\
1b
0d
1j
0l
17
1>
0F
1N
0V
0^
0f
b10001011 5
b1110100 +
b1110100 w
b1110100 $"
b1110100 )
b1110100 /
b1110100 1
b1110100 u
b1110100 y
0"
#963
b10000111 &
b10000111 .
b10000111 '"
0Q
0O
b1111011 4
0H
1I
0K
b10000111 -
b10000111 2
b10000111 #"
1p
0r
0J
0q
1s
0E
1m
b1110000 +
b1110000 w
b1110000 $"
b11111100 (
b11111100 |
b11111100 %"
b11111011 !
b11111011 0
b11111011 t
b11111011 x
#975
1"
#1000
b1110100 &
b1110100 .
b1110100 '"
1I
1?
1G
0$
09
1;
18
0A
1C
b1111011 4
1@
1Y
0[
1a
0c
1i
0k
b1110100 -
b1110100 2
b1110100 #"
0p
1r
13
1:
0<
1B
0D
0Z
1\
0b
1d
0j
1l
1q
0s
07
0>
1V
1^
1f
0n
b1111000 5
b10000011 +
b10000011 w
b10000011 $"
b10000111 )
b10000111 /
b10000111 1
b10000111 u
b10000111 y
0"
